ytmurl/__init__.py
ytmurl/get.py
ytmurl-3.0.0.dist-info/LICENSE
ytmurl-3.0.0.dist-info/METADATA
ytmurl-3.0.0.dist-info/WHEEL
ytmurl-3.0.0.dist-info/entry_points.txt
ytmurl-3.0.0.dist-info/top_level.txt
ytmurl-3.0.0.dist-info/RECORD
